Hardware/lights_7/light_7.v
module light_7 (clk, rst, number, led_1, led_2, led_3, led_4,led_5, led_6, led_7);

input clk;
input rst;
input [3:0] number;
output reg led_1;
output reg led_2;
output reg led_3;
output reg led_4;
output reg led_5;
output reg led_6;
output reg led_7;

reg [3:0] state;
reg [24:0] count;

always @(posedge clk) begin
	if (count == 25'd2500000) begin
		count <= 0;
		state <= state + 1;
	end
	else
		count <= count + 1;

end

always @(*) begin
	if (rst) begin
                led_1 <= 1'b0;
                led_2 <= 1'b0;
                led_3 <= 1'b0;
                led_4 <= 1'b0;
                led_5 <= 1'b0;
                led_6 <= 1'b0;
                led_7 <= 1'b0;
        end 
	else begin
		case(number)
		4'b0001: begin
                        led_1 <= 1'b1;
		        led_2 <= 1'b0;
		        led_3 <= 1'b0;
		        led_4 <= 1'b1;
		        led_5 <= 1'b1;
		        led_6 <= 1'b1;
		        led_7 <= 1'b1;
		end
		4'b0010: begin
                        led_1 <= 1'b0;
		        led_2 <= 1'b0;
		        led_3 <= 1'b1;
		        led_4 <= 1'b0;
		        led_5 <= 1'b0;
		        led_6 <= 1'b1;
		        led_7 <= 1'b0;
		end
		4'b0011: begin
			led_1 <= 1'b0;
		        led_2 <= 1'b0;
		        led_3 <= 1'b0;
		        led_4 <= 1'b0;
		        led_5 <= 1'b1;
		        led_6 <= 1'b1;
		        led_7 <= 1'b0;
		end
		4'b0100: begin
                        led_1 <= 1'b1;
		        led_2 <= 1'b0;
		        led_3 <= 1'b0;
		        led_4 <= 1'b1;
		        led_5 <= 1'b0;
		        led_6 <= 1'b1;
		        led_7 <= 1'b1;
		end
		4'b0101: begin
                        led_1 <= 1'b0;
                        led_2 <= 1'b1;
                        led_3 <= 1'b0;
                        led_4 <= 1'b1;
                        led_5 <= 1'b0;
                        led_6 <= 1'b0;
                        led_7 <= 1'b0;
                end
		4'b0110: begin
                        led_1 <= 1'b0;
                        led_2 <= 1'b1;
                        led_3 <= 1'b0;
                        led_4 <= 1'b0;
                        led_5 <= 1'b0;
                        led_6 <= 1'b0;
                        led_7 <= 1'b0;
                end
		4'b0111: begin
                        led_1 <= 1'b0;
                        led_2 <= 1'b0;
                        led_3 <= 1'b0;
                        led_4 <= 1'b1;
                        led_5 <= 1'b1;
                        led_6 <= 1'b1;
                        led_7 <= 1'b1;
                end
		4'b1000: begin
                        led_1 <= 1'b0;
                        led_2 <= 1'b0;
                        led_3 <= 1'b0;
                        led_4 <= 1'b0;
                        led_5 <= 1'b0;
                        led_6 <= 1'b0;
                        led_7 <= 1'b0;
                end
		4'b1001: begin
                        led_1 <= 1'b0;
                        led_2 <= 1'b0;
                        led_3 <= 1'b0;
                        led_4 <= 1'b0;
                        led_5 <= 1'b1;
                        led_6 <= 1'b0;
                        led_7 <= 1'b0;
                end
			
		default:
			state <= 4'b0000;
		
	endcase
end	
end
endmodule

Hardware/lights_7/tb.v
`timescale 1 ns/1 ps
module tb;

reg clk;
reg rst;
reg [3:0] number;
wire led_1;
wire led_2;
wire led_3;
wire led_4;
wire led_5;
wire led_6;
wire led_7;

initial begin
	$dumpfile("tb.vcd");
	$dumpvars();
end

light_7 light (
  	.clk(clk),
  	.rst(rst),
  	.number(number),
  	.led_1(led_1),
  	.led_2(led_2),
  	.led_3(led_3),
  	.led_4(led_4),
  	.led_5(led_5),
  	.led_6(led_6),
  	.led_7(led_7)
);


always #10 clk = ~clk;


initial begin
	clk = 0;
	rst = 1;
 	number = 0;

  	#10 rst = 0;

  	#10 number = 1;
  	#10 number = 2;
  	#10 number = 3;
  	#10 number = 4;
  	#10 number = 5;
  	#10 number = 6;
  	#10 number = 7;
  	#10 number = 8;
  	#10 number = 9;
	
  	#100 $finish;
end

endmodule

Hardware/lights_7/tb.vcd
$date
	Thu Jun  1 00:24:41 2023
$end
$version
	Icarus Verilog
$end
$timescale
	1ps
$end
$scope module tb $end
$var wire 1 ! led_7 $end
$var wire 1 " led_6 $end
$var wire 1 # led_5 $end
$var wire 1 $ led_4 $end
$var wire 1 % led_3 $end
$var wire 1 & led_2 $end
$var wire 1 ' led_1 $end
$var reg 1 ( clk $end
$var reg 4 ) number [3:0] $end
$var reg 1 * rst $end
$scope module light $end
$var wire 1 ( clk $end
$var wire 4 + number [3:0] $end
$var wire 1 * rst $end
$var reg 25 , count [24:0] $end
$var reg 1 ' led_1 $end
$var reg 1 & led_2 $end
$var reg 1 % led_3 $end
$var reg 1 $ led_4 $end
$var reg 1 # led_5 $end
$var reg 1 " led_6 $end
$var reg 1 ! led_7 $end
$var reg 4 - state [3:0] $end
$upscope $end
$upscope $end
$enddefinitions $end
#0
$dumpvars
bx -
bx ,
b0 +
1*
b0 )
0(
0'
0&
0%
0$
0#
0"
0!
$end
#10000
0*
1(
#20000
1!
1"
1#
1$
1'
b1 )
b1 +
0(
#30000
0!
0#
0$
1%
0'
b10 )
b10 +
1(
#40000
1#
0%
b11 )
b11 +
0(
#50000
1!
0#
1$
1'
b100 )
b100 +
1(
#60000
0!
0"
1&
0'
b101 )
b101 +
0(
#70000
0$
b110 )
b110 +
1(
#80000
1!
1"
1#
1$
0&
b111 )
b111 +
0(
#90000
0!
0"
0#
0$
b1000 )
b1000 +
1(
#100000
1#
b1001 )
b1001 +
0(
